mirth_client/__init__.py
mirth_client/channels.py
mirth_client/exceptions.py
mirth_client/mirth.py
mirth_client/models.py
mirth_client/py.typed
mirth_client-4.1.0.dist-info/LICENSE
mirth_client-4.1.0.dist-info/METADATA
mirth_client-4.1.0.dist-info/WHEEL
mirth_client-4.1.0.dist-info/RECORD
