Metadata-Version: 2.3
Name: mirth-client
Version: 4.1.0
Summary: Basic Python interface for Mirth Connect
Author: Joel Collins
Author-email: joel.collins@renalregistry.nhs.uk
Requires-Python: >=3.9,<4.0
Classifier: Programming Language :: Python :: 3
Classifier: Programming Language :: Python :: 3.9
Classifier: Programming Language :: Python :: 3.10
Classifier: Programming Language :: Python :: 3.11
Classifier: Programming Language :: Python :: 3.12
Classifier: Programming Language :: Python :: 3.13
Provides-Extra: docs
Requires-Dist: Sphinx (>=3.5.3,<6.0.0) ; extra == "docs"
Requires-Dist: httpx (>=0.23,<0.28.1)
Requires-Dist: pydantic (>=1.8.2,<3.0.0)
Requires-Dist: semver (>=2.13,<4.0)
Requires-Dist: sphinx-rtd-theme (>=0.5.1,<2.1.0) ; extra == "docs"
Requires-Dist: typing-extensions (>=3.10,<5.0)
Requires-Dist: xmltodict (>=0.12,<0.14)
